ezbuild/__init__.py
ezbuild/__main__.py
ezbuild/app.py
ezbuild/common/__init__.py
ezbuild/common/bash.py
ezbuild/common/butler.py
ezbuild/common/file.py
ezbuild/common/publish-workshop.py
ezbuild/common/steamcmd.py
ezbuild/common/unity.py
ezbuild/common/zlog.py
ezbuild/tests/__init__.py
ezbuild/tests/test.py
ezbuild/tests/test_unity.py
zbuild/__init__.py
zbuild/__main__.py
zbuild/app.py
zbuild/common/__init__.py
zbuild/common/bash.py
zbuild/common/butler.py
zbuild/common/file.py
zbuild/common/publish-workshop.py
zbuild/common/steamcmd.py
zbuild/common/unity.py
zbuild/common/zlog.py
zbuild/tests/__init__.py
zbuild/tests/test.py
zbuild/tests/test_unity.py
ezbuild_pkg_CzarZappy-0.0.1.dist-info/LICENSE
ezbuild_pkg_CzarZappy-0.0.1.dist-info/METADATA
ezbuild_pkg_CzarZappy-0.0.1.dist-info/WHEEL
ezbuild_pkg_CzarZappy-0.0.1.dist-info/top_level.txt
ezbuild_pkg_CzarZappy-0.0.1.dist-info/RECORD
