Metadata-Version: 2.1
Name: ezbuild-pkg-CzarZappy
Version: 0.0.1
Summary: A tool to help game developers build and publish their games
Home-page: https://github.com/CzarZappy/EZBuild
Author: CzarZappy
Author-email: zappy@ravenheartgames.com
License: UNKNOWN
Platform: UNKNOWN
Classifier: Programming Language :: Python :: 3
Classifier: License :: OSI Approved :: MIT License
Classifier: Operating System :: OS Independent
Requires-Python: >=3.6
